epyk_fabric/PkgImports.py
epyk_fabric/UI.py
epyk_fabric/__init__.py
epyk_fabric/_version.py
epyk_fabric/groups/FtwCompAlerts.py
epyk_fabric/groups/FtwCompBtns.py
epyk_fabric/groups/FtwCompLists.py
epyk_fabric/groups/__init__.py
epyk_fabric/html/HtmlFtwForms.py
epyk_fabric/html/__init__.py
epyk_fabric-0.0.2.dist-info/LICENSE
epyk_fabric-0.0.2.dist-info/METADATA
epyk_fabric-0.0.2.dist-info/WHEEL
epyk_fabric-0.0.2.dist-info/top_level.txt
epyk_fabric-0.0.2.dist-info/RECORD
