Metadata-Version: 2.1
Name: epyk-fabric
Version: 0.0.2
Summary: Epyk extension linked to the Office UI components
Home-page: https://github.com/epykure/epyk-fabric
Author: epykure
Author-email: smith.pyotr@gmail.com
Project-URL: Documentation, http://www.epyk.io
Project-URL: Library, https://github.com/OfficeDev/office-ui-fabric-core
Project-URL: Code, https://github.com/epykure/epyk-fabric
Classifier: Programming Language :: Python :: 3
Classifier: License :: OSI Approved :: GNU General Public License (GPL)
Classifier: Operating System :: OS Independent
Requires-Python: >=3.8
License-File: LICENSE
Requires-Dist: epyk
